mkdocs_roamlinks_plugin_extra/__init__.py
mkdocs_roamlinks_plugin_extra/plugin.py
tests/__init__.py
tests/test_plugin.py
mkdocs_roamlinks_plugin_extra-0.3.5.dist-info/LICENSE
mkdocs_roamlinks_plugin_extra-0.3.5.dist-info/METADATA
mkdocs_roamlinks_plugin_extra-0.3.5.dist-info/WHEEL
mkdocs_roamlinks_plugin_extra-0.3.5.dist-info/entry_points.txt
mkdocs_roamlinks_plugin_extra-0.3.5.dist-info/top_level.txt
mkdocs_roamlinks_plugin_extra-0.3.5.dist-info/RECORD
