Metadata-Version: 2.1
Name: mkdocs-roamlinks-plugin-extra
Version: 0.3.5
Summary: Fork of @Jackiexiao mkdocs-roamlinks-plugin package with added support for special chars.
Home-page: https://github.com/harttraveller/mkdocs-roamlinks-plugin-extra
Author: harttraveller
License: MIT
Keywords: mkdocs
Classifier: Development Status :: 4 - Beta
Classifier: Intended Audience :: Developers
Classifier: Intended Audience :: Information Technology
Classifier: License :: OSI Approved :: MIT License
Classifier: Programming Language :: Python
Classifier: Programming Language :: Python :: 3.6
Classifier: Programming Language :: Python :: 3.7
Classifier: Programming Language :: Python :: 3.8
Classifier: Programming Language :: Python :: 3.9
Requires-Python: >=3.6
License-File: LICENSE
Requires-Dist: mkdocs >=1.0.4
Provides-Extra: dev
Requires-Dist: pytest ; extra == 'dev'
